MANIFEST.in
README.rst
netflix.py
setup.py
python_netflix.egg-info/PKG-INFO
python_netflix.egg-info/SOURCES.txt
python_netflix.egg-info/dependency_links.txt
python_netflix.egg-info/requires.txt
python_netflix.egg-info/top_level.txt