Metadata-Version: 1.0
Name: python-netflix
Version: 0.3.0
Summary: A Python Library to interface with Netflix REST API & OAuth
Home-page: https://github.com/michaelhelmick/python-netflix/
Author: Mike Helmick
Author-email: mikehelmick@me.com
License: MIT License
Download-URL: https://github.com/michaelhelmick/python-netflix/zipball/master
Keywords: python netflix oauth api
Platform: UNKNOWN
Classifier: Development Status :: 4 - Beta
Classifier: Intended Audience :: Developers
Classifier: License :: OSI Approved :: MIT License
Classifier: Topic :: Software Development :: Libraries :: Python Modules
Classifier: Topic :: Communications :: Chat
Classifier: Topic :: Internet
